wavinfo/__init__.py
wavinfo/__main__.py
wavinfo/man/man1/wavinfo.1
wavinfo/man/man7/wavinfo.7
wavinfo/rf64_parser.py
wavinfo/riff_parser.py
wavinfo/umid_parser.py
wavinfo/wave_adm_reader.py
wavinfo/wave_bext_reader.py
wavinfo/wave_cues_reader.py
wavinfo/wave_dbmd_reader.py
wavinfo/wave_info_reader.py
wavinfo/wave_ixml_reader.py
wavinfo/wave_reader.py
wavinfo/wave_smpl_reader.py
wavinfo/wavfind.py
wavinfo-4.0.0.dist-info/WHEEL
wavinfo-4.0.0.dist-info/entry_points.txt
wavinfo-4.0.0.dist-info/METADATA
wavinfo-4.0.0.dist-info/RECORD
