Metadata-Version: 2.4
Name: wavinfo
Version: 4.0.0
Summary: Probe WAVE files for all metadata
Keywords: waveform,metadata,audio,ebu,smpte,avi,library,film,broadcast
Author: Jamie Hardt
Author-email: Jamie Hardt <jamiehardt@me.com>
License-Expression: MIT
Classifier: Development Status :: 5 - Production/Stable
Classifier: License :: OSI Approved :: MIT License
Classifier: Topic :: Multimedia
Classifier: Topic :: Multimedia :: Sound/Audio
Classifier: Programming Language :: Python :: 3.9
Classifier: Programming Language :: Python :: 3.10
Classifier: Programming Language :: Python :: 3.11
Classifier: Programming Language :: Python :: 3.12
Classifier: Programming Language :: Python :: 3.13
Classifier: Programming Language :: Python :: 3.14
Requires-Dist: lxml>=6.0.2
Requires-Python: >=3.8
Project-URL: Tracker, https://github.com/iluvcapra/wavinfo/issues
